ortho_view_napari/__init__.py
ortho_view_napari/_dock_widget.py
ortho_view_napari/_version.py
ortho_view_napari/_tests/__init__.py
ortho_view_napari/_tests/test_dock_widget.py
ortho_view_napari-0.1.1.dist-info/LICENSE
ortho_view_napari-0.1.1.dist-info/METADATA
ortho_view_napari-0.1.1.dist-info/WHEEL
ortho_view_napari-0.1.1.dist-info/entry_points.txt
ortho_view_napari-0.1.1.dist-info/top_level.txt
ortho_view_napari-0.1.1.dist-info/RECORD
