Metadata-Version: 2.1
Name: ortho-view-napari
Version: 0.1.1
Summary: It displays the lateral view of the current 3D stack. This could be a starting point for a orthorviewer.
Home-page: https://github.com/JoOkuma/ortho-view-napari
Author: Jordao Bragantini
Author-email: jordao.bragantini@czbiohub.org
License: BSD-3
Project-URL: Bug Tracker, https://github.com/JoOkuma/ortho-view-napari/issues
Project-URL: Documentation, https://github.com/JoOkuma/ortho-view-napari#README.md
Project-URL: Source Code, https://github.com/JoOkuma/ortho-view-napari
Project-URL: User Support, https://github.com/JoOkuma/ortho-view-napari/issues
Platform: UNKNOWN
Classifier: Development Status :: 2 - Pre-Alpha
Classifier: Intended Audience :: Developers
Classifier: Framework :: napari
Classifier: Topic :: Software Development :: Testing
Classifier: Programming Language :: Python
Classifier: Programming Language :: Python :: 3
Classifier: Programming Language :: Python :: 3.7
Classifier: Programming Language :: Python :: 3.8
Classifier: Programming Language :: Python :: 3.9
Classifier: Operating System :: OS Independent
Classifier: License :: OSI Approved :: BSD License
Requires-Python: >=3.7
License-File: LICENSE
Requires-Dist: napari-plugin-engine (>=0.1.4)
Requires-Dist: numpy
